kivymt/__init__.py
kivymt/datetime_editor.py
kivymt/fix_kivy.py
kivymt/image_btn.py
kivymt/playpause_btn.py
kivymt/spinner_ext.py
kivymt/calendar/__init__.py
kivymt/calendar/calendar_data.py
kivymt/calendar/calendar_ui.py
kivymt/circulardatetimepicker/__init__.py
kivymt/circularlayout/__init__.py
kivymt/data/buttons-0.png
kivymt/data/icons.atlas
kivymt/data/new-md.png
kivymt/data/revert-512.png
kivymt/data/save.png
kivymt-0.0.2.dist-info/DESCRIPTION.rst
kivymt-0.0.2.dist-info/METADATA
kivymt-0.0.2.dist-info/RECORD
kivymt-0.0.2.dist-info/WHEEL
kivymt-0.0.2.dist-info/metadata.json
kivymt-0.0.2.dist-info/top_level.txt
