Metadata-Version: 2.0
Name: kivymt
Version: 0.0.2
Summary: Extra Kivy modules written by Minh-Tri Pham
Home-page: UNKNOWN
Author: ['Minh-Tri Pham']
Author-email: UNKNOWN
License: UNKNOWN
Platform: UNKNOWN
Requires-Dist: basemt
Requires-Dist: kivy
Requires-Dist: kivy-garden
Requires-Dist: pygame
